{
 "kind": "CubeQueryTableSchema",
 "id": "0c7a5946f512b9ea13282eeae59a5c20d8ddb9e4818abeac1b6aee94b8b28523",
 "isDeleted": false,
 "rev": "",
 "description": "",
 "name": "column",
 "acl": {
  "kind": "Acl",
  "owner": "",
  "aces": []
 },
 "createdDate": {
  "kind": "Date",
  "value": ""
 },
 "lastModifiedDate": {
  "kind": "Date",
  "value": ""
 },
 "urls": [],
 "tags": [],
 "meta": [
  {
   "kind": "Pair",
   "key": "count..PredictedPopulation_Population.size_in_bytes",
   "value": "416"
  },
  {
   "kind": "Pair",
   "key": "SHA256",
   "value": "0c7a5946f512b9ea13282eeae59a5c20d8ddb9e4818abeac1b6aee94b8b28523"
  }
 ],
 "url": {
  "kind": "Url",
  "uri": ""
 },
 "version": "",
 "isPublic": false,
 "projectId": "",
 "folderId": "",
 "nRows": 12,
 "columns": [
  {
   "kind": "ColumnSchema",
   "id": "51957873-07d3-4056-8070-55ff4236a067",
   "name": "count..PredictedPopulation_Population",
   "type": "string",
   "nRows": 0,
   "size": -1,
   "metaData": {
    "kind": "ColumnSchemaMetaData",
    "sort": [],
    "ascending": true,
    "quartiles": [],
    "properties": []
   }
  }
 ],
 "dataDirectory": "data/0c/7a/0c7a5946f512b9ea13282eeae59a5c20d8ddb9e4818abeac1b6aee94b8b28523",
 "relation": {
  "kind": "Relation",
  "id": "20e01881-196a-4c01-a14a-6df3e4cac104"
 },
 "queryHash": "57d36fdae0f099a472b164e85078a6a2",
 "queryTableType": "column",
 "query": {
  "kind": "CubeQuery",
  "relation": {
   "kind": "Relation",
   "id": "2fa23ebb-f976-4144-84a5-c3c4675b44c8"
  },
  "colColumns": [],
  "rowColumns": [],
  "axisQueries": [],
  "filters": {
   "kind": "Filters",
   "removeNaN": true,
   "namedFilters": []
  },
  "operatorSettings": {
   "kind": "OperatorSettings",
   "namespace": "",
   "operatorRef": {
    "kind": "OperatorRef",
    "name": "",
    "version": "",
    "operatorId": "",
    "operatorKind": "",
    "propertyValues": [],
    "url": {
     "kind": "Url",
     "uri": ""
    },
    "operatorSpec": {
     "kind": "OperatorSpec",
     "ontologyUri": "",
     "ontologyVersion": "",
     "inputSpecs": [],
     "outputSpecs": []
    }
   },
   "environment": [],
   "operatorModel": {
    "kind": "OperatorModel"
   }
  },
  "qtHash": "",
  "columnHash": "",
  "rowHash": ""
 }
}